nerve/__init__.py
nerve/__main__.py
nerve/applications/__init__.py
nerve/applications/audio.py
nerve/applications/bluetooth.py
nerve/applications/fonts.py
nerve/applications/shell.py
nerve/default_profiles/__init__.py
nerve/default_profiles/desktop.py
nerve/default_profiles/minimal.py
nerve/default_profiles/profile.py
nerve/default_profiles/server.py
nerve/default_profiles/xorg.py
nerve/default_profiles/desktops/__init__.py
nerve/default_profiles/desktops/awesome.py
nerve/default_profiles/desktops/bspwm.py
nerve/default_profiles/desktops/budgie.py
nerve/default_profiles/desktops/cinnamon.py
nerve/default_profiles/desktops/cosmic.py
nerve/default_profiles/desktops/cutefish.py
nerve/default_profiles/desktops/deepin.py
nerve/default_profiles/desktops/enlightenment.py
nerve/default_profiles/desktops/gnome.py
nerve/default_profiles/desktops/hyprland.py
nerve/default_profiles/desktops/i3.py
nerve/default_profiles/desktops/labwc.py
nerve/default_profiles/desktops/lxqt.py
nerve/default_profiles/desktops/mate.py
nerve/default_profiles/desktops/niri.py
nerve/default_profiles/desktops/pantheon.py
nerve/default_profiles/desktops/plasma.py
nerve/default_profiles/desktops/qtile.py
nerve/default_profiles/desktops/river.py
nerve/default_profiles/desktops/sway.py
nerve/default_profiles/desktops/xfce4.py
nerve/default_profiles/desktops/xmonad.py
nerve/default_profiles/servers/__init__.py
nerve/default_profiles/servers/cockpit.py
nerve/default_profiles/servers/docker.py
nerve/default_profiles/servers/httpd.py
nerve/default_profiles/servers/lighttpd.py
nerve/default_profiles/servers/mariadb.py
nerve/default_profiles/servers/nginx.py
nerve/default_profiles/servers/postgresql.py
nerve/default_profiles/servers/sshd.py
nerve/default_profiles/servers/tomcat.py
nerve/lib/__init__.py
nerve/lib/args.py
nerve/lib/boot.py
nerve/lib/configuration.py
nerve/lib/crypt.py
nerve/lib/exceptions.py
nerve/lib/general.py
nerve/lib/global_menu.py
nerve/lib/hardware.py
nerve/lib/installer.py
nerve_tui-1.1.1.dist-info/METADATA
nerve_tui-1.1.1.dist-info/WHEEL
nerve_tui-1.1.1.dist-info/entry_points.txt
nerve_tui-1.1.1.dist-info/top_level.txt
nerve_tui-1.1.1.dist-info/RECORD
