Metadata-Version: 2.4
Name: nerve-tui
Version: 1.1.1
Summary: Nerve - an intuitive and powerful system installation tool.
Author-email: CELESTIFYX Team <celestifyx@gmail.com>
License-Expression: GPL-3.0-or-later
Project-URL: Home, https://gitlab.com/nerve-dev/nerve
Project-URL: Repository, https://gitlab.com/nerve-dev/nerve.git
Project-URL: Issues, https://gitlab.com/nerve-dev/nerve/-/issues
Keywords: linux,arch,nerve,installer
Classifier: Programming Language :: Python :: 3.12
Classifier: Operating System :: POSIX :: Linux
Requires-Python: >=3.12
Requires-Dist: pyparted>=3.13.0
Requires-Dist: pydantic==2.12.3
Requires-Dist: cryptography>=45.0.7
Requires-Dist: textual>=5.3.0
Provides-Extra: log
Requires-Dist: systemd_python==235; extra == "log"
Provides-Extra: dev
Requires-Dist: mypy==1.18.2; extra == "dev"
Requires-Dist: flake8==7.3.0; extra == "dev"
Requires-Dist: ruff==0.14.3; extra == "dev"
Requires-Dist: pylint==4.0.2; extra == "dev"
Provides-Extra: doc
Requires-Dist: sphinx; extra == "doc"
